README.md
boot.py
config.py
requirements.txt
setup.py
./README.md
./boot.py
./config.py
./requirements.txt
component/__init__.py
component/captcha.py
component/env.py
component/function.py
component/logging.py
component/session.py
database/__init__.py
database/core.py
database/model.py
database/query.py
database/setttings.py
database/builder/__init__.py
database/builder/base.py
database/builder/generate.py
database/builder/mysql.py
database/connector/__init__.py
database/connector/connection.py
database/connector/mysql.py
database/contain/__init__.py
database/contain/columns.py
database/contain/component.py
database/contain/db.py
database/contain/func.py
database/example/__init__.py
database/example/generate.py
database/example/model.py
database/example/query.py
quickpython_mvc.egg-info/PKG-INFO
quickpython_mvc.egg-info/SOURCES.txt
quickpython_mvc.egg-info/dependency_links.txt
quickpython_mvc.egg-info/requires.txt
quickpython_mvc.egg-info/top_level.txt
server/__init__.py
server/exception.py
server/processor.py
server/server.py
server/settings.py
server/contain/__init__.py
server/contain/controller.py