Metadata-Version: 2.1
Name: quickpython-mvc
Version: 0.1.3
Summary: Python rapid development framework .
Home-page: https://github.com/quickpython
Author: lo106258
Author-email: lo106258@gmail.com
License: MIT Licence
Keywords: quickpython-mvc,quickpython,quick,WEB,database,MVC
Platform: any
